circuitsvis/__init__.py
circuitsvis/activations.py
circuitsvis/attention.py
circuitsvis/dist/cdn/iife.js
circuitsvis/dist/cdn/iife.js.map
circuitsvis/examples.py
circuitsvis/logits.py
circuitsvis/tests/__init__.py
circuitsvis/tests/snapshots/__init__.py
circuitsvis/tests/snapshots/snap_test_activations.py
circuitsvis/tests/snapshots/snap_test_attention.py
circuitsvis/tests/snapshots/snap_test_hello.py
circuitsvis/tests/snapshots/snap_test_render.py
circuitsvis/tests/snapshots/snap_test_tokens.py
circuitsvis/tests/snapshots/snap_test_topk_samples.py
circuitsvis/tests/snapshots/snap_test_topk_tokens.py
circuitsvis/tests/test_activations.py
circuitsvis/tests/test_attention.py
circuitsvis/tests/test_hello.py
circuitsvis/tests/test_init.py
circuitsvis/tests/test_tokens.py
circuitsvis/tests/test_topk_samples.py
circuitsvis/tests/test_topk_tokens.py
circuitsvis/tokens.py
circuitsvis/topk_samples.py
circuitsvis/topk_tokens.py
circuitsvis/utils/build_js.py
circuitsvis/utils/convert_props.py
circuitsvis/utils/render.py
circuitsvis/utils/tests/__init__.py
circuitsvis/utils/tests/snapshots/__init__.py
circuitsvis/utils/tests/snapshots/snap_test_render.py
circuitsvis/utils/tests/test_convert_props.py
circuitsvis/utils/tests/test_render.py
circuitsvis-1.43.3.dist-info/LICENSE.txt
circuitsvis-1.43.3.dist-info/METADATA
circuitsvis-1.43.3.dist-info/WHEEL
circuitsvis-1.43.3.dist-info/RECORD
