Metadata-Version: 2.1
Name: circuitsvis
Version: 1.43.3
Summary: Mechanistic Interpretability Visualizations
License: MIT
Author: Alan Cooney
Author-email: 41682961+alan-cooney@users.noreply.github.com
Requires-Python: >=3.8
Classifier: License :: OSI Approved :: MIT License
Classifier: Programming Language :: Python :: 3
Classifier: Programming Language :: Python :: 3.8
Classifier: Programming Language :: Python :: 3.9
Classifier: Programming Language :: Python :: 3.10
Classifier: Programming Language :: Python :: 3.11
Requires-Dist: importlib-metadata (>=5.1.0)
Requires-Dist: numpy (>=1.20,<1.25) ; python_version >= "3.8" and python_version < "3.9"
Requires-Dist: numpy (>=1.24) ; python_version >= "3.9" and python_version < "3.12"
Requires-Dist: numpy (>=1.26) ; python_version >= "3.12" and python_version < "3.13"
Requires-Dist: torch (>=2.1.1)
